django_logto/__init__.py
django_logto/apps.py
django_logto/authentication.py
django_logto/django_logto_client.py
django_logto/logto_backend.py
django_logto/logto_init.py
django_logto/models.py
django_logto/urls.py
django_logto/utils.py
django_logto/views.py
django_logto/migrations/0001_initial.py
django_logto/migrations/__init__.py
django_logto-1.0.4.dist-info/LICENSE
django_logto-1.0.4.dist-info/METADATA
django_logto-1.0.4.dist-info/WHEEL
django_logto-1.0.4.dist-info/top_level.txt
django_logto-1.0.4.dist-info/RECORD
