Metadata-Version: 2.1
Name: django-logto
Version: 1.0.4
Summary: DRF and Django Logto integration
Home-page: https://github.com/pulsation-studio/django-logto
Author: Pulsation Studio
Author-email: liam@pulsation.eco
License-File: LICENSE
Requires-Dist: django >=4.0
Requires-Dist: djangorestframework >=3.0
Requires-Dist: python-jose
Requires-Dist: asgiref
Requires-Dist: urllib3
Requires-Dist: logto
Requires-Dist: requests
